ritl/__init__.py
ritl/relative_import.py
testdir/__init__.py
testdir/testscript.py
ritl-0.1.1.dist-info/LICENSE
ritl-0.1.1.dist-info/METADATA
ritl-0.1.1.dist-info/WHEEL
ritl-0.1.1.dist-info/top_level.txt
ritl-0.1.1.dist-info/RECORD
