Metadata-Version: 2.1
Name: ritl
Version: 0.1.1
Summary: Relatives Import Tool
Home-page: https://github.com/Guitheg/ritl
Author: Guitheg
Author-email: UNKNOWN
License: MIT
Platform: UNKNOWN
Classifier: Programming Language :: Python
Classifier: Development Status :: 2 - Pre-Alpha
Classifier: License :: OSI Approved :: MIT License
Classifier: Natural Language :: English
Classifier: Operating System :: OS Independent
Classifier: Programming Language :: Python :: 3 :: Only
Classifier: Topic :: Education
